setup.py
beacon/__init__.py
novabeacon.egg-info/PKG-INFO
novabeacon.egg-info/SOURCES.txt
novabeacon.egg-info/dependency_links.txt
novabeacon.egg-info/not-zip-safe
novabeacon.egg-info/top_level.txt