Metadata-Version: 1.0
Name: novabeacon
Version: 0.1
Summary: Python lib to save event for beacon.
Home-page: https://github.com/novagile/novabeacon
Author: Novapost
Author-email: boris.feld@novapost.fr
License: Public Domain
Platform: UNKNOWN
